api_foundry_query_engine/.pre-commit-config.yaml
api_foundry_query_engine/__init__.py
api_foundry_query_engine/lambda_handler.py
api_foundry_query_engine/operation.py
api_foundry_query_engine/adapters/adapter.py
api_foundry_query_engine/adapters/case_change_adapter.py
api_foundry_query_engine/adapters/gateway_adapter.py
api_foundry_query_engine/adapters/security_adapter.py
api_foundry_query_engine/connectors/connection.py
api_foundry_query_engine/connectors/connection_factory.py
api_foundry_query_engine/connectors/oracle_connector.py
api_foundry_query_engine/connectors/postgres_connection.py
api_foundry_query_engine/dao/batch_operation_handler.py
api_foundry_query_engine/dao/dao.py
api_foundry_query_engine/dao/operation_dao.py
api_foundry_query_engine/dao/sql_custom_query_handler.py
api_foundry_query_engine/dao/sql_delete_query_handler.py
api_foundry_query_engine/dao/sql_insert_query_handler.py
api_foundry_query_engine/dao/sql_query_handler.py
api_foundry_query_engine/dao/sql_restore_query_handler.py
api_foundry_query_engine/dao/sql_select_query_handler.py
api_foundry_query_engine/dao/sql_subselect_query_handler.py
api_foundry_query_engine/dao/sql_update_query_handler.py
api_foundry_query_engine/services/service.py
api_foundry_query_engine/services/transactional_service.py
api_foundry_query_engine/utils/api_model.py
api_foundry_query_engine/utils/app_exception.py
api_foundry_query_engine/utils/claims_check.py
api_foundry_query_engine/utils/dependency_resolver.py
api_foundry_query_engine/utils/logger.py
api_foundry_query_engine/utils/reference_resolver.py
api_foundry_query_engine/utils/token_decoder.py
api_foundry_query_engine-0.8.58.dist-info/METADATA
api_foundry_query_engine-0.8.58.dist-info/WHEEL
api_foundry_query_engine-0.8.58.dist-info/licenses/LICENSE
api_foundry_query_engine-0.8.58.dist-info/RECORD
